[
    {
        "result": {
            "data": [
                {
                    "id": "bitcoin",
                    "rank": "1",
                    "symbol": "BTC",
                    "name": "Bitcoin",
                    "supply": "19460625.0000000000000000",
                    "maxSupply": "21000000.0000000000000000",
                    "marketCapUsd": "505361543468.8466482758455625",
                    "volumeUsd24Hr": "2332543245.0919927891216826",
                    "priceUsd": "25968.4128063125746617",
                    "changePercent24Hr": "-0.3581128113444491",
                    "vwap24Hr": "26056.5246677872930689",
                    "explorer": "https://blockchain.info/"
                },
                {
                    "id": "ethereum",
                    "rank": "2",
                    "symbol": "ETH",
                    "name": "Ethereum",
                    "supply": "120131756.1693597400000000",
                    "maxSupply": null,
                    "marketCapUsd": "197286154758.2074310173473654",
                    "volumeUsd24Hr": "1292428081.7152393912785118",
                    "priceUsd": "1642.2481536029217013",
                    "changePercent24Hr": "-0.3200350528968384",
                    "vwap24Hr": "1650.3759905793794835",
                    "explorer": "https://etherscan.io/"
                },
                {
                    "id": "tether",
                    "rank": "3",
                    "symbol": "USDT",
                    "name": "Tether",
                    "supply": "82842337234.0993000000000000",
                    "maxSupply": null,
                    "marketCapUsd": "82819518536.4653161582183344",
                    "volumeUsd24Hr": "5188832666.8171998018863471",
                    "priceUsd": "0.9997245527058284",
                    "changePercent24Hr": "-0.0071277056358752",
                    "vwap24Hr": "0.9994076527744953",
                    "explorer": "https://www.omniexplorer.info/asset/31"
                },
                {
                    "id": "binance-coin",
                    "rank": "4",
                    "symbol": "BNB",
                    "name": "BNB",
                    "supply": "166801148.0000000000000000",
                    "maxSupply": "166801148.0000000000000000",
                    "marketCapUsd": "36239562886.0486198528990028",
                    "volumeUsd24Hr": "92670206.9266866950507344",
                    "priceUsd": "217.2620711582190061",
                    "changePercent24Hr": "-0.0037738527114659",
                    "vwap24Hr": "218.1807246667342140",
                    "explorer": "https://etherscan.io/token/0xB8c77482e45F1F44dE1745F52C74426C631bDD52"
                },
                {
                    "id": "usd-coin",
                    "rank": "5",
                    "symbol": "USDC",
                    "name": "USD Coin",
                    "supply": "26258163462.1215630000000000",
                    "maxSupply": null,
                    "marketCapUsd": "26267141211.8661483982070406",
                    "volumeUsd24Hr": "406558478.9170140370283330",
                    "priceUsd": "1.0003419031859382",
                    "changePercent24Hr": "-0.0053729517867540",
                    "vwap24Hr": "1.0005764589270488",
                    "explorer": "https://etherscan.io/token/0xa0b86991c6218b36c1d19d4a2e9eb0ce3606eb48"
                },
                {
                    "id": "xrp",
                    "rank": "6",
                    "symbol": "XRP",
                    "name": "XRP",
                    "supply": "45404028640.0000000000000000",
                    "maxSupply": "100000000000.0000000000000000",
                    "marketCapUsd": "23407984411.3623488391106720",
                    "volumeUsd24Hr": "315413983.1265501744893183",
                    "priceUsd": "0.5155486222810723",
                    "changePercent24Hr": "-0.4780380188931117",
                    "vwap24Hr": "0.5194269421118213",
                    "explorer": "https://xrpcharts.ripple.com/#/graph/"
                },
                {
                    "id": "cardano",
                    "rank": "7",
                    "symbol": "ADA",
                    "name": "Cardano",
                    "supply": "35048010482.3520000000000000",
                    "maxSupply": "45000000000.0000000000000000",
                    "marketCapUsd": "9146141419.9771797912567538",
                    "volumeUsd24Hr": "53056519.8647847548631625",
                    "priceUsd": "0.2609603596353239",
                    "changePercent24Hr": "-0.2343035701810367",
                    "vwap24Hr": "0.2645452225111068",
                    "explorer": "https://cardanoexplorer.com/"
                },
                {
                    "id": "dogecoin",
                    "rank": "8",
                    "symbol": "DOGE",
                    "name": "Dogecoin",
                    "supply": "140634406383.7052000000000000",
                    "maxSupply": null,
                    "marketCapUsd": "8796962566.2319089427446105",
                    "volumeUsd24Hr": "62146182.5910414606949772",
                    "priceUsd": "0.0625519941558994",
                    "changePercent24Hr": "-0.0081111710918254",
                    "vwap24Hr": "0.0631134060329248",
                    "explorer": "http://dogechain.info/chain/Dogecoin"
                },
                {
                    "id": "solana",
                    "rank": "9",
                    "symbol": "SOL",
                    "name": "Solana",
                    "supply": "407234211.5003290000000000",
                    "maxSupply": null,
                    "marketCapUsd": "8201808352.8029320675547846",
                    "volumeUsd24Hr": "46959894.5894281437811477",
                    "priceUsd": "20.1402733885885860",
                    "changePercent24Hr": "-1.8239301260122323",
                    "vwap24Hr": "20.4812669232592694",
                    "explorer": "https://explorer.solana.com/"
                },
                {
                    "id": "tron",
                    "rank": "10",
                    "symbol": "TRX",
                    "name": "TRON",
                    "supply": "89442500282.2074100000000000",
                    "maxSupply": null,
                    "marketCapUsd": "6808804482.3571759240525877",
                    "volumeUsd24Hr": "43111487.6073670250981700",
                    "priceUsd": "0.0761249345766739",
                    "changePercent24Hr": "-1.2917963263168918",
                    "vwap24Hr": "0.0766411257111845",
                    "explorer": "https://tronscan.org/#/"
                },
                {
                    "id": "polkadot",
                    "rank": "11",
                    "symbol": "DOT",
                    "name": "Polkadot",
                    "supply": "1269133464.8069100000000000",
                    "maxSupply": null,
                    "marketCapUsd": "5783977552.0755717370217189",
                    "volumeUsd24Hr": "49807205.4498447565287693",
                    "priceUsd": "4.5574226135117826",
                    "changePercent24Hr": "1.8477599815842521",
                    "vwap24Hr": "4.5848973932214998",
                    "explorer": "https://polkascan.io/polkadot"
                },
                {
                    "id": "multi-collateral-dai",
                    "rank": "12",
                    "symbol": "DAI",
                    "name": "Multi Collateral DAI",
                    "supply": "5347888595.7464075000000000",
                    "maxSupply": null,
                    "marketCapUsd": "5348213490.1413490206772381",
                    "volumeUsd24Hr": "5891585.8141996416816413",
                    "priceUsd": "1.0000607519003294",
                    "changePercent24Hr": "0.0506165017537366",
                    "vwap24Hr": "0.9995261077497256",
                    "explorer": "https://etherscan.io/token/0x89d24a6b4ccb1b6faa2625fe562bdd9a23260359"
                },
                {
                    "id": "polygon",
                    "rank": "13",
                    "symbol": "MATIC",
                    "name": "Polygon",
                    "supply": "9319469069.2849300000000000",
                    "maxSupply": "10000000000.0000000000000000",
                    "marketCapUsd": "5165755113.5356600197260209",
                    "volumeUsd24Hr": "84139757.6553812914848806",
                    "priceUsd": "0.5542971466648176",
                    "changePercent24Hr": "-1.0349169006103089",
                    "vwap24Hr": "0.5603928104192323",
                    "explorer": "https://etherscan.io/token/0x7D1AfA7B718fb893dB30A3aBc0Cfc608AaCfeBB0"
                },
                {
                    "id": "litecoin",
                    "rank": "14",
                    "symbol": "LTC",
                    "name": "Litecoin",
                    "supply": "73552914.2274352800000000",
                    "maxSupply": "84000000.0000000000000000",
                    "marketCapUsd": "4769855140.4461568065180929",
                    "volumeUsd24Hr": "71889884.6712354696890793",
                    "priceUsd": "64.8493019011746791",
                    "changePercent24Hr": "0.0539886032195185",
                    "vwap24Hr": "65.2765602464683324",
                    "explorer": "http://explorer.litecoin.net/chain/Litecoin"
                },
                {
                    "id": "shiba-inu",
                    "rank": "15",
                    "symbol": "SHIB",
                    "name": "Shiba Inu",
                    "supply": "589346914631298.1000000000000000",
                    "maxSupply": null,
                    "marketCapUsd": "4752027712.3974872734915393",
                    "volumeUsd24Hr": "46085173.8790400162774890",
                    "priceUsd": "0.0000080632096214",
                    "changePercent24Hr": "0.5871490492671133",
                    "vwap24Hr": "0.0000081640442002",
                    "explorer": "https://etherscan.io/token/0x95ad61b0a150d79219dcf64e1e6cc01f0b64c4ce"
                }
            ]
        }
    }
]
